spacr/__init__.py
spacr/__main__.py
spacr/app_annotate.py
spacr/app_classify.py
spacr/app_make_masks.py
spacr/app_mask.py
spacr/app_measure.py
spacr/app_sequencing.py
spacr/app_umap.py
spacr/chat_bot.py
spacr/core.py
spacr/deep_spacr.py
spacr/gui.py
spacr/gui_core.py
spacr/gui_elements.py
spacr/gui_utils.py
spacr/io.py
spacr/logger.py
spacr/measure.py
spacr/mediar.py
spacr/ml.py
spacr/openai.py
spacr/plot.py
spacr/sequencing.py
spacr/settings.py
spacr/sim.py
spacr/sp_stats.py
spacr/spacr_cellpose.py
spacr/submodules.py
spacr/timelapse.py
spacr/toxo.py
spacr/utils.py
spacr/version.py
spacr/resources/data/lopit.csv
spacr/resources/data/toxoplasma_metadata.csv
spacr/resources/font/open_sans/OFL.txt
"spacr/resources/font/open_sans/OpenSans-Italic-VariableFont_wdth,wght.ttf"
"spacr/resources/font/open_sans/OpenSans-VariableFont_wdth,wght.ttf"
spacr/resources/font/open_sans/README.txt
spacr/resources/font/open_sans/static/OpenSans-Bold.ttf
spacr/resources/font/open_sans/static/OpenSans-BoldItalic.ttf
spacr/resources/font/open_sans/static/OpenSans-ExtraBold.ttf
spacr/resources/font/open_sans/static/OpenSans-ExtraBoldItalic.ttf
spacr/resources/font/open_sans/static/OpenSans-Italic.ttf
spacr/resources/font/open_sans/static/OpenSans-Light.ttf
spacr/resources/font/open_sans/static/OpenSans-LightItalic.ttf
spacr/resources/font/open_sans/static/OpenSans-Medium.ttf
spacr/resources/font/open_sans/static/OpenSans-MediumItalic.ttf
spacr/resources/font/open_sans/static/OpenSans-Regular.ttf
spacr/resources/font/open_sans/static/OpenSans-SemiBold.ttf
spacr/resources/font/open_sans/static/OpenSans-SemiBoldItalic.ttf
spacr/resources/font/open_sans/static/OpenSans_Condensed-Bold.ttf
spacr/resources/font/open_sans/static/OpenSans_Condensed-BoldItalic.ttf
spacr/resources/font/open_sans/static/OpenSans_Condensed-ExtraBold.ttf
spacr/resources/font/open_sans/static/OpenSans_Condensed-ExtraBoldItalic.ttf
spacr/resources/font/open_sans/static/OpenSans_Condensed-Italic.ttf
spacr-1.1.3.dist-info/LICENSE
spacr-1.1.3.dist-info/METADATA
spacr-1.1.3.dist-info/WHEEL
spacr-1.1.3.dist-info/entry_points.txt
spacr-1.1.3.dist-info/top_level.txt
spacr-1.1.3.dist-info/RECORD
