Metadata-Version: 2.1
Name: spacr
Version: 1.1.3
Summary: Spatial phenotype analysis of crisp screens (SpaCr)
Home-page: https://github.com/EinarOlafsson/spacr
Author: Einar Birnir Olafsson
Author-email: olafsson@med.umich.com
Classifier: Programming Language :: Python :: 3
Classifier: License :: OSI Approved :: MIT License
Classifier: Operating System :: OS Independent
License-File: LICENSE
Requires-Dist: numpy <2.0,>=1.26.4
Requires-Dist: pandas <3.0,>=2.2.1
Requires-Dist: scipy <2.0,>=1.12.0
Requires-Dist: cellpose <5.0,>=4.0
Requires-Dist: segment-anything
Requires-Dist: scikit-image <1.0,>=0.22.0
Requires-Dist: scikit-learn <2.0,>=1.4.1
Requires-Dist: scikit-posthocs <0.20,>=0.10.0
Requires-Dist: mahotas <2.0,>=1.4.13
Requires-Dist: btrack <1.0,>=0.6.5
Requires-Dist: trackpy <1.0,>=0.6.2
Requires-Dist: statsmodels <1.0,>=0.14.1
Requires-Dist: shap <1.0,>=0.45.0
Requires-Dist: torch <3.0,>=2.0
Requires-Dist: torchvision <1.0,>=0.1
Requires-Dist: torch-geometric <3.0,>=2.5
Requires-Dist: torchcam <1.0,>=0.4.0
Requires-Dist: transformers <5.0,>=4.45.2
Requires-Dist: segmentation-models-pytorch >=0.3.3
Requires-Dist: monai >=1.3.0
Requires-Dist: captum <1.0,>=0.7.0
Requires-Dist: seaborn <1.0,>=0.13.2
Requires-Dist: matplotlib <4.0,>=3.8.3
Requires-Dist: matplotlib-venn <2.0,>=1.1
Requires-Dist: adjustText <2.0,>=1.2.0
Requires-Dist: bottleneck <2.0,>=1.3.6
Requires-Dist: numexpr <3.0,>=2.8.4
Requires-Dist: opencv-python-headless <5.0,>=4.9.0.80
Requires-Dist: pillow <11.0,>=10.2.0
Requires-Dist: tifffile >=2023.4.12
Requires-Dist: nd2reader <4.0,>=3.3.0
Requires-Dist: czifile
Requires-Dist: pylibCZIrw <6.0,>=5.0.0
Requires-Dist: aicspylibczi
Requires-Dist: readlif
Requires-Dist: imageio <3.0,>=2.34.0
Requires-Dist: pingouin <1.0,>=0.5.5
Requires-Dist: umap-learn <1.0,>=0.5.6
Requires-Dist: ttkthemes <4.0,>=3.2.2
Requires-Dist: xgboost <3.0,>=2.0.3
Requires-Dist: PyWavelets <2.0,>=1.6.0
Requires-Dist: ttf-opensans >=2020.10.30
Requires-Dist: customtkinter <6.0,>=5.2.2
Requires-Dist: biopython <2.0,>=1.80
Requires-Dist: lxml <6.0,>=5.1.0
Requires-Dist: psutil <6.0,>=5.9.8
Requires-Dist: gputil <2.0,>=1.4.0
Requires-Dist: gpustat <2.0,>=1.1.1
Requires-Dist: pyautogui <1.0,>=0.9.54
Requires-Dist: tables <4.0,>=3.8.0
Requires-Dist: rapidfuzz <4.0,>=3.9
Requires-Dist: keyring <16.0,>=15.1
Requires-Dist: screeninfo <1.0,>=0.8.1
Requires-Dist: fastremap >=1.14.1
Requires-Dist: pytz >=2023.3.post1
Requires-Dist: tqdm >=4.65.0
Requires-Dist: wandb >=0.16.2
Requires-Dist: openai <2.0,>=1.50.2
Requires-Dist: gdown
Requires-Dist: IPython <9.0,>=8.18.1
Requires-Dist: ipykernel
Requires-Dist: ipywidgets <9.0,>=8.1.2
Requires-Dist: brokenaxes <1.0,>=0.6.2
Requires-Dist: huggingface-hub <0.25,>=0.24.0
Provides-Extra: dev
Requires-Dist: pytest <3.12,>=3.9 ; extra == 'dev'
Provides-Extra: full
Requires-Dist: opencv-python ; extra == 'full'
Provides-Extra: headless
Requires-Dist: opencv-python-headless ; extra == 'headless'
